racrypt/__init__.py
racrypt/libra_lib.dylib
racrypt/libra_lib.so
racrypt/ra_lib.dll
racrypt-0.1.dist-info/LICENSE
racrypt-0.1.dist-info/METADATA
racrypt-0.1.dist-info/WHEEL
racrypt-0.1.dist-info/top_level.txt
racrypt-0.1.dist-info/RECORD
