Metadata-Version: 2.1
Name: racrypt
Version: 0.1
Summary: use c-code crypto in python
Home-page: https://github.com/rasmartguy/racrypt
Author: Rasmart team
Author-email: rasmarutil@gmail.com
License: UNKNOWN
Platform: UNKNOWN
Classifier: Programming Language :: Python :: 3
Classifier: License :: OSI Approved :: MIT License
Classifier: Operating System :: OS Independent
